setup.py
ovhapi/OvhApi.py
ovhapi/__init__.py
ovhapi.egg-info/PKG-INFO
ovhapi.egg-info/SOURCES.txt
ovhapi.egg-info/dependency_links.txt
ovhapi.egg-info/top_level.txt