Metadata-Version: 1.0
Name: ovhapi
Version: 2.1
Summary: Python module to manage OVH API
Home-page: https://github.com/optiflows/OvhApi
Author: Guilhem Lettron
Author-email: guilhem.lettron@optiflows.com
License: UNKNOWN
Platform: UNKNOWN
